[{"crash_date":"2026-06-01T00:00:00.000","crash_time":"11:47","latitude":"40.71945","longitude":"-73.98217","cross_street_name":"219       STANTON ST","number_of_persons_injured":"0","number_of_pedestrians_injured":"0","number_of_pedestrians_killed":"0","number_of_cyclist_injured":"0","number_of_cyclist_killed":"0","number_of_motorist_injured":"0","number_of_motorist_killed":"0","collision_id":"4903192"}
,{"crash_date":"2026-06-01T00:00:00.000","crash_time":"12:00","latitude":"40.738697","longitude":"-73.94092","on_street_name":"BORDEN AVE","off_street_name":"REVIEW AVE","number_of_persons_injured":"0","number_of_pedestrians_injured":"0","number_of_pedestrians_killed":"0","number_of_cyclist_injured":"0","number_of_cyclist_killed":"0","number_of_motorist_injured":"0","number_of_motorist_killed":"0","collision_id":"4903421"}
,{"crash_date":"2026-06-01T00:00:00.000","crash_time":"13:00","latitude":"40.710735","longitude":"-73.96181","on_street_name":"DRIGGS AVE","off_street_name":"S 5 ST","number_of_persons_injured":"0","number_of_pedestrians_injured":"0","number_of_pedestrians_killed":"0","number_of_cyclist_injured":"0","number_of_cyclist_killed":"0","number_of_motorist_injured":"0","number_of_motorist_killed":"0","collision_id":"4903777"}
,{"crash_date":"2026-06-01T00:00:00.000","crash_time":"13:00","latitude":"40.71539","longitude":"-73.9931","cross_street_name":"83        CANAL ST","number_of_persons_injured":"0","number_of_pedestrians_injured":"0","number_of_pedestrians_killed":"0","number_of_cyclist_injured":"0","number_of_cyclist_killed":"0","number_of_motorist_injured":"0","number_of_motorist_killed":"0","collision_id":"4904050"}
,{"crash_date":"2026-06-01T00:00:00.000","crash_time":"14:00","latitude":"40.719864","longitude":"-73.94486","on_street_name":"BROOKLYN QUEENS EXPRESSWAY","number_of_persons_injured":"2","number_of_pedestrians_injured":"0","number_of_pedestrians_killed":"0","number_of_cyclist_injured":"0","number_of_cyclist_killed":"0","number_of_motorist_injured":"2","number_of_motorist_killed":"0","collision_id":"4903811"}
,{"crash_date":"2026-06-01T00:00:00.000","crash_time":"14:30","latitude":"40.70793","longitude":"-73.95613","cross_street_name":"341       BROADWAY","number_of_persons_injured":"0","number_of_pedestrians_injured":"0","number_of_pedestrians_killed":"0","number_of_cyclist_injured":"0","number_of_cyclist_killed":"0","number_of_motorist_injured":"0","number_of_motorist_killed":"0","collision_id":"4903257"}
,{"crash_date":"2026-06-01T00:00:00.000","crash_time":"14:45","latitude":"40.714165","longitude":"-74.00631","on_street_name":"BROADWAY","off_street_name":"CHAMBERS ST","number_of_persons_injured":"1","number_of_pedestrians_injured":"1","number_of_pedestrians_killed":"0","number_of_cyclist_injured":"0","number_of_cyclist_killed":"0","number_of_motorist_injured":"0","number_of_motorist_killed":"0","collision_id":"4903612"}
,{"crash_date":"2026-06-01T00:00:00.000","crash_time":"15:06","latitude":"40.74339","longitude":"-73.986145","on_street_name":"MADISON AVE","off_street_name":"E 27 ST","number_of_persons_injured":"0","number_of_pedestrians_injured":"0","number_of_pedestrians_killed":"0","number_of_cyclist_injured":"0","number_of_cyclist_killed":"0","number_of_motorist_injured":"0","number_of_motorist_killed":"0","collision_id":"4903314"}
,{"crash_date":"2026-06-01T00:00:00.000","crash_time":"16:57","latitude":"40.72255","longitude":"-74.0063","on_street_name":"CANAL ST","off_street_name":"VARICK ST","number_of_persons_injured":"0","number_of_pedestrians_injured":"0","number_of_pedestrians_killed":"0","number_of_cyclist_injured":"0","number_of_cyclist_killed":"0","number_of_motorist_injured":"0","number_of_motorist_killed":"0","collision_id":"4903618"}
,{"crash_date":"2026-06-01T00:00:00.000","crash_time":"17:10","latitude":"40.73579","longitude":"-73.98536","on_street_name":"E 18 ST","number_of_persons_injured":"0","number_of_pedestrians_injured":"0","number_of_pedestrians_killed":"0","number_of_cyclist_injured":"0","number_of_cyclist_killed":"0","number_of_motorist_injured":"0","number_of_motorist_killed":"0","collision_id":"4903454"}
,{"crash_date":"2026-06-01T00:00:00.000","crash_time":"18:40","latitude":"40.736103","longitude":"-73.98912","cross_street_name":"40        UNION SQ E","number_of_persons_injured":"0","number_of_pedestrians_injured":"0","number_of_pedestrians_killed":"0","number_of_cyclist_injured":"0","number_of_cyclist_killed":"0","number_of_motorist_injured":"0","number_of_motorist_killed":"0","collision_id":"4903605"}
,{"crash_date":"2026-06-01T00:00:00.000","crash_time":"4:50","latitude":"40.709183","longitude":"-73.956825","on_street_name":"BROOKLYN QUEENS EXPRESSWAY","number_of_persons_injured":"2","number_of_pedestrians_injured":"0","number_of_pedestrians_killed":"0","number_of_cyclist_injured":"0","number_of_cyclist_killed":"0","number_of_motorist_injured":"2","number_of_motorist_killed":"0","collision_id":"4903251"}
,{"crash_date":"2026-06-01T00:00:00.000","crash_time":"8:44","latitude":"40.73817","longitude":"-73.9776","on_street_name":"E 25 ST","number_of_persons_injured":"1","number_of_pedestrians_injured":"0","number_of_pedestrians_killed":"0","number_of_cyclist_injured":"1","number_of_cyclist_killed":"0","number_of_motorist_injured":"0","number_of_motorist_killed":"0","collision_id":"4903079"}
,{"crash_date":"2026-06-02T00:00:00.000","crash_time":"12:35","latitude":"40.708084","longitude":"-74.0034","on_street_name":"BEEKMAN ST","off_street_name":"PEARL ST","number_of_persons_injured":"0","number_of_pedestrians_injured":"0","number_of_pedestrians_killed":"0","number_of_cyclist_injured":"0","number_of_cyclist_killed":"0","number_of_motorist_injured":"0","number_of_motorist_killed":"0","collision_id":"4903620"}
,{"crash_date":"2026-06-02T00:00:00.000","crash_time":"12:54","latitude":"40.719883","longitude":"-73.98302","cross_street_name":"196       STANTON ST","number_of_persons_injured":"0","number_of_pedestrians_injured":"0","number_of_pedestrians_killed":"0","number_of_cyclist_injured":"0","number_of_cyclist_killed":"0","number_of_motorist_injured":"0","number_of_motorist_killed":"0","collision_id":"4903481"}
,{"crash_date":"2026-06-02T00:00:00.000","crash_time":"13:05","latitude":"40.736664","longitude":"-73.98451","cross_street_name":"237       3 AVE","number_of_persons_injured":"1","number_of_pedestrians_injured":"0","number_of_pedestrians_killed":"0","number_of_cyclist_injured":"1","number_of_cyclist_killed":"0","number_of_motorist_injured":"0","number_of_motorist_killed":"0","collision_id":"4903455"}
,{"crash_date":"2026-06-02T00:00:00.000","crash_time":"13:46","latitude":"40.735764","longitude":"-73.97491","on_street_name":"FDR DRIVE","number_of_persons_injured":"2","number_of_pedestrians_injured":"0","number_of_pedestrians_killed":"0","number_of_cyclist_injured":"0","number_of_cyclist_killed":"0","number_of_motorist_injured":"2","number_of_motorist_killed":"0","collision_id":"4904355"}
,{"crash_date":"2026-06-02T00:00:00.000","crash_time":"14:31","latitude":"40.725426","longitude":"-73.990204","cross_street_name":"47        2 AVE","number_of_persons_injured":"1","number_of_pedestrians_injured":"1","number_of_pedestrians_killed":"0","number_of_cyclist_injured":"0","number_of_cyclist_killed":"0","number_of_motorist_injured":"0","number_of_motorist_killed":"0","collision_id":"4903963"}
,{"crash_date":"2026-06-02T00:00:00.000","crash_time":"1:44","latitude":"40.736893","longitude":"-74.0085","cross_street_name":"55        BETHUNE ST","number_of_persons_injured":"0","number_of_pedestrians_injured":"0","number_of_pedestrians_killed":"0","number_of_cyclist_injured":"0","number_of_cyclist_killed":"0","number_of_motorist_injured":"0","number_of_motorist_killed":"0","collision_id":"4903853"}
,{"crash_date":"2026-06-02T00:00:00.000","crash_time":"15:15","latitude":"40.711685","longitude":"-73.960526","cross_street_name":"182       S 3 ST","number_of_persons_injured":"0","number_of_pedestrians_injured":"0","number_of_pedestrians_killed":"0","number_of_cyclist_injured":"0","number_of_cyclist_killed":"0","number_of_motorist_injured":"0","number_of_motorist_killed":"0","collision_id":"4903550"}
,{"crash_date":"2026-06-02T00:00:00.000","crash_time":"15:15","latitude":"40.71714","longitude":"-73.99745","cross_street_name":"94        MOTT ST","number_of_persons_injured":"1","number_of_pedestrians_injured":"1","number_of_pedestrians_killed":"0","number_of_cyclist_injured":"0","number_of_cyclist_killed":"0","number_of_motorist_injured":"0","number_of_motorist_killed":"0","collision_id":"4904051"}
,{"crash_date":"2026-06-02T00:00:00.000","crash_time":"16:45","latitude":"40.736164","longitude":"-73.97891","on_street_name":"1 AVE","off_street_name":"E 22 ST","number_of_persons_injured":"1","number_of_pedestrians_injured":"1","number_of_pedestrians_killed":"0","number_of_cyclist_injured":"0","number_of_cyclist_killed":"0","number_of_motorist_injured":"0","number_of_motorist_killed":"0","collision_id":"4903460"}
,{"crash_date":"2026-06-02T00:00:00.000","crash_time":"16:49","latitude":"40.711365","longitude":"-73.97897","on_street_name":"FDR DRIVE","number_of_persons_injured":"1","number_of_pedestrians_injured":"0","number_of_pedestrians_killed":"0","number_of_cyclist_injured":"0","number_of_cyclist_killed":"0","number_of_motorist_injured":"1","number_of_motorist_killed":"0","collision_id":"4904018"}
,{"crash_date":"2026-06-02T00:00:00.000","crash_time":"18:00","latitude":"40.70879","longitude":"-74.00086","on_street_name":"DOVER ST","off_street_name":"WATER ST","number_of_persons_injured":"0","number_of_pedestrians_injured":"0","number_of_pedestrians_killed":"0","number_of_cyclist_injured":"0","number_of_cyclist_killed":"0","number_of_motorist_injured":"0","number_of_motorist_killed":"0","collision_id":"4903619"}
,{"crash_date":"2026-06-02T00:00:00.000","crash_time":"18:33","latitude":"40.742256","longitude":"-73.977684","on_street_name":"E 30 ST","off_street_name":"2 AVE","number_of_persons_injured":"1","number_of_pedestrians_injured":"1","number_of_pedestrians_killed":"0","number_of_cyclist_injured":"0","number_of_cyclist_killed":"0","number_of_motorist_injured":"0","number_of_motorist_killed":"0","collision_id":"4903730"}
,{"crash_date":"2026-06-02T00:00:00.000","crash_time":"18:56","latitude":"40.72662","longitude":"-73.98691","cross_street_name":"336       E 6 ST","number_of_persons_injured":"0","number_of_pedestrians_injured":"0","number_of_pedestrians_killed":"0","number_of_cyclist_injured":"0","number_of_cyclist_killed":"0","number_of_motorist_injured":"0","number_of_motorist_killed":"0","collision_id":"4903775"}
,{"crash_date":"2026-06-02T00:00:00.000","crash_time":"19:10","latitude":"40.708797","longitude":"-74.01085","on_street_name":"BROADWAY","off_street_name":"CEDAR ST","number_of_persons_injured":"0","number_of_pedestrians_injured":"0","number_of_pedestrians_killed":"0","number_of_cyclist_injured":"0","number_of_cyclist_killed":"0","number_of_motorist_injured":"0","number_of_motorist_killed":"0","collision_id":"4904592"}
,{"crash_date":"2026-06-02T00:00:00.000","crash_time":"21:29","latitude":"40.712463","longitude":"-73.9924","on_street_name":"PIKE ST","off_street_name":"MADISON ST","number_of_persons_injured":"1","number_of_pedestrians_injured":"0","number_of_pedestrians_killed":"0","number_of_cyclist_injured":"1","number_of_cyclist_killed":"0","number_of_motorist_injured":"0","number_of_motorist_killed":"0","collision_id":"4905024"}
,{"crash_date":"2026-06-02T00:00:00.000","crash_time":"21:53","latitude":"40.742523","longitude":"-73.949234","on_street_name":"49 AVE","off_street_name":"21 ST","number_of_persons_injured":"0","number_of_pedestrians_injured":"0","number_of_pedestrians_killed":"0","number_of_cyclist_injured":"0","number_of_cyclist_killed":"0","number_of_motorist_injured":"0","number_of_motorist_killed":"0","collision_id":"4903519"}
,{"crash_date":"2026-06-02T00:00:00.000","crash_time":"23:44","latitude":"40.708942","longitude":"-73.94176","on_street_name":"HUMBOLDT ST","off_street_name":"SCHOLES ST","number_of_persons_injured":"1","number_of_pedestrians_injured":"1","number_of_pedestrians_killed":"0","number_of_cyclist_injured":"0","number_of_cyclist_killed":"0","number_of_motorist_injured":"0","number_of_motorist_killed":"0","collision_id":"4903556"}
,{"crash_date":"2026-06-02T00:00:00.000","crash_time":"7:57","latitude":"40.72084","longitude":"-74.00066","on_street_name":"GRAND ST","off_street_name":"BROADWAY","number_of_persons_injured":"0","number_of_pedestrians_injured":"0","number_of_pedestrians_killed":"0","number_of_cyclist_injured":"0","number_of_cyclist_killed":"0","number_of_motorist_injured":"0","number_of_motorist_killed":"0","collision_id":"4904965"}
,{"crash_date":"2026-06-02T00:00:00.000","crash_time":"8:30","latitude":"40.742733","longitude":"-73.97856","cross_street_name":"227       E 30 ST","number_of_persons_injured":"0","number_of_pedestrians_injured":"0","number_of_pedestrians_killed":"0","number_of_cyclist_injured":"0","number_of_cyclist_killed":"0","number_of_motorist_injured":"0","number_of_motorist_killed":"0","collision_id":"4903343"}
,{"crash_date":"2026-06-02T00:00:00.000","crash_time":"9:30","latitude":"40.727695","longitude":"-74.00463","cross_street_name":"50        KING ST","number_of_persons_injured":"0","number_of_pedestrians_injured":"0","number_of_pedestrians_killed":"0","number_of_cyclist_injured":"0","number_of_cyclist_killed":"0","number_of_motorist_injured":"0","number_of_motorist_killed":"0","collision_id":"4904970"}
,{"crash_date":"2026-06-02T00:00:00.000","crash_time":"9:30","latitude":"40.71931","longitude":"-74.009834","cross_street_name":"187       FRANKLIN ST","number_of_persons_injured":"0","number_of_pedestrians_injured":"0","number_of_pedestrians_killed":"0","number_of_cyclist_injured":"0","number_of_cyclist_killed":"0","number_of_motorist_injured":"0","number_of_motorist_killed":"0","collision_id":"4904975"}
,{"crash_date":"2026-06-02T00:00:00.000","crash_time":"9:50","latitude":"40.71473","longitude":"-73.96676","on_street_name":"KENT AVE","off_street_name":"S 2 ST","number_of_persons_injured":"1","number_of_pedestrians_injured":"0","number_of_pedestrians_killed":"0","number_of_cyclist_injured":"1","number_of_cyclist_killed":"0","number_of_motorist_injured":"0","number_of_motorist_killed":"0","collision_id":"4903675"}
,{"crash_date":"2026-06-03T00:00:00.000","crash_time":"0:00","latitude":"40.712463","longitude":"-73.9924","on_street_name":"PIKE ST","off_street_name":"MADISON ST","number_of_persons_injured":"0","number_of_pedestrians_injured":"0","number_of_pedestrians_killed":"0","number_of_cyclist_injured":"0","number_of_cyclist_killed":"0","number_of_motorist_injured":"0","number_of_motorist_killed":"0","collision_id":"4904722"}
,{"crash_date":"2026-06-03T00:00:00.000","crash_time":"11:23","latitude":"40.719395","longitude":"-74.001884","on_street_name":"CANAL ST","off_street_name":"BROADWAY","number_of_persons_injured":"0","number_of_pedestrians_injured":"0","number_of_pedestrians_killed":"0","number_of_cyclist_injured":"0","number_of_cyclist_killed":"0","number_of_motorist_injured":"0","number_of_motorist_killed":"0","collision_id":"4903663"}
,{"crash_date":"2026-06-03T00:00:00.000","crash_time":"11:40","latitude":"40.71104","longitude":"-74.01455","on_street_name":"WEST ST","off_street_name":"LIBERTY ST","number_of_persons_injured":"0","number_of_pedestrians_injured":"0","number_of_pedestrians_killed":"0","number_of_cyclist_injured":"0","number_of_cyclist_killed":"0","number_of_motorist_injured":"0","number_of_motorist_killed":"0","collision_id":"4905485"}
,{"crash_date":"2026-06-03T00:00:00.000","crash_time":"12:35","latitude":"40.717075","longitude":"-74.00625","on_street_name":"CHURCH ST","off_street_name":"WORTH ST","number_of_persons_injured":"0","number_of_pedestrians_injured":"0","number_of_pedestrians_killed":"0","number_of_cyclist_injured":"0","number_of_cyclist_killed":"0","number_of_motorist_injured":"0","number_of_motorist_killed":"0","collision_id":"4905495"}
,{"crash_date":"2026-06-03T00:00:00.000","crash_time":"13:00","latitude":"40.725876","longitude":"-73.996216","cross_street_name":"622       BROADWAY","number_of_persons_injured":"1","number_of_pedestrians_injured":"0","number_of_pedestrians_killed":"0","number_of_cyclist_injured":"1","number_of_cyclist_killed":"0","number_of_motorist_injured":"0","number_of_motorist_killed":"0","collision_id":"4905254"}
,{"crash_date":"2026-06-03T00:00:00.000","crash_time":"14:07","latitude":"40.715794","longitude":"-73.99056","on_street_name":"LUDLOW ST","off_street_name":"HESTER ST","number_of_persons_injured":"1","number_of_pedestrians_injured":"1","number_of_pedestrians_killed":"0","number_of_cyclist_injured":"0","number_of_cyclist_killed":"0","number_of_motorist_injured":"0","number_of_motorist_killed":"0","collision_id":"4903994"}
,{"crash_date":"2026-06-03T00:00:00.000","crash_time":"14:45","latitude":"40.714733","longitude":"-73.95908","cross_street_name":"658       DRIGGS AVE","number_of_persons_injured":"1","number_of_pedestrians_injured":"0","number_of_pedestrians_killed":"0","number_of_cyclist_injured":"0","number_of_cyclist_killed":"0","number_of_motorist_injured":"1","number_of_motorist_killed":"0","collision_id":"4903872"}
,{"crash_date":"2026-06-03T00:00:00.000","crash_time":"15:45","latitude":"40.737885","longitude":"-73.9809","on_street_name":"2 AVE","off_street_name":"E 23 ST","number_of_persons_injured":"1","number_of_pedestrians_injured":"0","number_of_pedestrians_killed":"0","number_of_cyclist_injured":"1","number_of_cyclist_killed":"0","number_of_motorist_injured":"0","number_of_motorist_killed":"0","collision_id":"4903871"}
,{"crash_date":"2026-06-03T00:00:00.000","crash_time":"17:05","latitude":"40.713474","longitude":"-73.99859","on_street_name":"WORTH ST","off_street_name":"CHATHAM SQ","number_of_persons_injured":"0","number_of_pedestrians_injured":"0","number_of_pedestrians_killed":"0","number_of_cyclist_injured":"0","number_of_cyclist_killed":"0","number_of_motorist_injured":"0","number_of_motorist_killed":"0","collision_id":"4904055"}
,{"crash_date":"2026-06-03T00:00:00.000","crash_time":"17:05","latitude":"40.713726","longitude":"-73.99878","cross_street_name":"1         MOTT ST","number_of_persons_injured":"1","number_of_pedestrians_injured":"1","number_of_pedestrians_killed":"0","number_of_cyclist_injured":"0","number_of_cyclist_killed":"0","number_of_motorist_injured":"0","number_of_motorist_killed":"0","collision_id":"4904056"}
,{"crash_date":"2026-06-03T00:00:00.000","crash_time":"17:30","latitude":"40.72729","longitude":"-73.99364","on_street_name":"GREAT JONES ST","off_street_name":"LAFAYETTE ST","number_of_persons_injured":"0","number_of_pedestrians_injured":"0","number_of_pedestrians_killed":"0","number_of_cyclist_injured":"0","number_of_cyclist_killed":"0","number_of_motorist_injured":"0","number_of_motorist_killed":"0","collision_id":"4903962"}
,{"crash_date":"2026-06-03T00:00:00.000","crash_time":"18:20","latitude":"40.72326","longitude":"-73.988434","on_street_name":"E 1 ST","off_street_name":"1 AVE","number_of_persons_injured":"1","number_of_pedestrians_injured":"0","number_of_pedestrians_killed":"0","number_of_cyclist_injured":"1","number_of_cyclist_killed":"0","number_of_motorist_injured":"0","number_of_motorist_killed":"0","collision_id":"4904609"}
,{"crash_date":"2026-06-03T00:00:00.000","crash_time":"18:25","latitude":"40.7138","longitude":"-74.00883","on_street_name":"MURRAY ST","number_of_persons_injured":"1","number_of_pedestrians_injured":"0","number_of_pedestrians_killed":"0","number_of_cyclist_injured":"0","number_of_cyclist_killed":"0","number_of_motorist_injured":"1","number_of_motorist_killed":"0","collision_id":"4904968"}
,{"crash_date":"2026-06-03T00:00:00.000","crash_time":"20:10","latitude":"40.712646","longitude":"-73.989975","on_street_name":"MADISON ST","off_street_name":"RUTGERS ST","number_of_persons_injured":"1","number_of_pedestrians_injured":"1","number_of_pedestrians_killed":"0","number_of_cyclist_injured":"0","number_of_cyclist_killed":"0","number_of_motorist_injured":"0","number_of_motorist_killed":"0","collision_id":"4904496"}
,{"crash_date":"2026-06-03T00:00:00.000","crash_time":"23:28","latitude":"40.742588","longitude":"-73.980415","on_street_name":"E 29 ST","number_of_persons_injured":"1","number_of_pedestrians_injured":"1","number_of_pedestrians_killed":"0","number_of_cyclist_injured":"0","number_of_cyclist_killed":"0","number_of_motorist_injured":"0","number_of_motorist_killed":"0","collision_id":"4904260"}
,{"crash_date":"2026-06-03T00:00:00.000","crash_time":"23:50","latitude":"40.721596","longitude":"-73.97476","on_street_name":"E 6 ST","off_street_name":"FRANKLIN D ROOSEVELT DR","number_of_persons_injured":"2","number_of_pedestrians_injured":"0","number_of_pedestrians_killed":"0","number_of_cyclist_injured":"0","number_of_cyclist_killed":"0","number_of_motorist_injured":"2","number_of_motorist_killed":"0","collision_id":"4903780"}
,{"crash_date":"2026-06-03T00:00:00.000","crash_time":"9:38","latitude":"40.739586","longitude":"-73.98919","cross_street_name":"20        E 21 ST","number_of_persons_injured":"1","number_of_pedestrians_injured":"0","number_of_pedestrians_killed":"0","number_of_cyclist_injured":"1","number_of_cyclist_killed":"0","number_of_motorist_injured":"0","number_of_motorist_killed":"0","collision_id":"4903646"}
,{"crash_date":"2026-06-03T00:00:00.000","crash_time":"9:50","latitude":"40.74389","longitude":"-73.98705","cross_street_name":"7         E 27 ST","number_of_persons_injured":"0","number_of_pedestrians_injured":"0","number_of_pedestrians_killed":"0","number_of_cyclist_injured":"0","number_of_cyclist_killed":"0","number_of_motorist_injured":"0","number_of_motorist_killed":"0","collision_id":"4903630"}
,{"crash_date":"2026-06-04T00:00:00.000","crash_time":"12:30","latitude":"40.74209","longitude":"-73.991264","cross_street_name":"40        W 23 ST","number_of_persons_injured":"1","number_of_pedestrians_injured":"0","number_of_pedestrians_killed":"0","number_of_cyclist_injured":"1","number_of_cyclist_killed":"0","number_of_motorist_injured":"0","number_of_motorist_killed":"0","collision_id":"4904003"}
,{"crash_date":"2026-06-04T00:00:00.000","crash_time":"14:30","latitude":"40.73524","longitude":"-73.98433","cross_street_name":"222       E 18 ST","number_of_persons_injured":"0","number_of_pedestrians_injured":"0","number_of_pedestrians_killed":"0","number_of_cyclist_injured":"0","number_of_cyclist_killed":"0","number_of_motorist_injured":"0","number_of_motorist_killed":"0","collision_id":"4904259"}
,{"crash_date":"2026-06-04T00:00:00.000","crash_time":"16:21","latitude":"40.718304","longitude":"-73.9874","on_street_name":"NORFOLK ST","off_street_name":"DELANCEY ST","number_of_persons_injured":"0","number_of_pedestrians_injured":"0","number_of_pedestrians_killed":"0","number_of_cyclist_injured":"0","number_of_cyclist_killed":"0","number_of_motorist_injured":"0","number_of_motorist_killed":"0","collision_id":"4904017"}
,{"crash_date":"2026-06-04T00:00:00.000","crash_time":"16:21","latitude":"40.713486","longitude":"-73.96551","on_street_name":"S 3 ST","off_street_name":"WYTHE AVE","number_of_persons_injured":"0","number_of_pedestrians_injured":"0","number_of_pedestrians_killed":"0","number_of_cyclist_injured":"0","number_of_cyclist_killed":"0","number_of_motorist_injured":"0","number_of_motorist_killed":"0","collision_id":"4904554"}
,{"crash_date":"2026-06-04T00:00:00.000","crash_time":"16:22","latitude":"40.730442","longitude":"-73.98034","on_street_name":"E 14 ST","off_street_name":"AVENUE A","number_of_persons_injured":"1","number_of_pedestrians_injured":"0","number_of_pedestrians_killed":"0","number_of_cyclist_injured":"1","number_of_cyclist_killed":"0","number_of_motorist_injured":"0","number_of_motorist_killed":"0","collision_id":"4903991"}
,{"crash_date":"2026-06-04T00:00:00.000","crash_time":"16:53","latitude":"40.737545","longitude":"-73.984085","on_street_name":"E 21 ST","off_street_name":"3 AVE","number_of_persons_injured":"0","number_of_pedestrians_injured":"0","number_of_pedestrians_killed":"0","number_of_cyclist_injured":"0","number_of_cyclist_killed":"0","number_of_motorist_injured":"0","number_of_motorist_killed":"0","collision_id":"4904154"}
,{"crash_date":"2026-06-04T00:00:00.000","crash_time":"17:03","latitude":"40.722458","longitude":"-73.996895","cross_street_name":"233       LAFAYETTE ST","number_of_persons_injured":"1","number_of_pedestrians_injured":"1","number_of_pedestrians_killed":"0","number_of_cyclist_injured":"0","number_of_cyclist_killed":"0","number_of_motorist_injured":"0","number_of_motorist_killed":"0","collision_id":"4905468"}
,{"crash_date":"2026-06-04T00:00:00.000","crash_time":"17:05","latitude":"40.733505","longitude":"-73.97708","cross_street_name":"520       E 20 ST","number_of_persons_injured":"0","number_of_pedestrians_injured":"0","number_of_pedestrians_killed":"0","number_of_cyclist_injured":"0","number_of_cyclist_killed":"0","number_of_motorist_injured":"0","number_of_motorist_killed":"0","collision_id":"4904653"}
,{"crash_date":"2026-06-04T00:00:00.000","crash_time":"20:20","latitude":"40.722397","longitude":"-73.993","cross_street_name":"235       BOWERY","number_of_persons_injured":"1","number_of_pedestrians_injured":"0","number_of_pedestrians_killed":"0","number_of_cyclist_injured":"1","number_of_cyclist_killed":"0","number_of_motorist_injured":"0","number_of_motorist_killed":"0","collision_id":"4904270"}
,{"crash_date":"2026-06-04T00:00:00.000","crash_time":"21:15","latitude":"40.726147","longitude":"-73.958046","cross_street_name":"90        QUAY ST","number_of_persons_injured":"0","number_of_pedestrians_injured":"0","number_of_pedestrians_killed":"0","number_of_cyclist_injured":"0","number_of_cyclist_killed":"0","number_of_motorist_injured":"0","number_of_motorist_killed":"0","collision_id":"4904073"}
,{"crash_date":"2026-06-04T00:00:00.000","crash_time":"22:30","latitude":"40.7224","longitude":"-73.991646","on_street_name":"STANTON ST","off_street_name":"CHRYSTIE ST","number_of_persons_injured":"1","number_of_pedestrians_injured":"0","number_of_pedestrians_killed":"0","number_of_cyclist_injured":"1","number_of_cyclist_killed":"0","number_of_motorist_injured":"0","number_of_motorist_killed":"0","collision_id":"4904716"}
,{"crash_date":"2026-06-04T00:00:00.000","crash_time":"9:20","latitude":"40.71727","longitude":"-73.96285","on_street_name":"N 3 ST","off_street_name":"WYTHE AVE","number_of_persons_injured":"0","number_of_pedestrians_injured":"0","number_of_pedestrians_killed":"0","number_of_cyclist_injured":"0","number_of_cyclist_killed":"0","number_of_motorist_injured":"0","number_of_motorist_killed":"0","collision_id":"4904316"}
,{"crash_date":"2026-06-05T00:00:00.000","crash_time":"10:15","latitude":"40.740875","longitude":"-73.98798","on_street_name":"MADISON AVE","off_street_name":"E 23 ST","number_of_persons_injured":"0","number_of_pedestrians_injured":"0","number_of_pedestrians_killed":"0","number_of_cyclist_injured":"0","number_of_cyclist_killed":"0","number_of_motorist_injured":"0","number_of_motorist_killed":"0","collision_id":"4904513"}
,{"crash_date":"2026-06-05T00:00:00.000","crash_time":"10:49","latitude":"40.718796","longitude":"-73.98901","on_street_name":"DELANCEY ST","off_street_name":"LUDLOW ST","number_of_persons_injured":"0","number_of_pedestrians_injured":"0","number_of_pedestrians_killed":"0","number_of_cyclist_injured":"0","number_of_cyclist_killed":"0","number_of_motorist_injured":"0","number_of_motorist_killed":"0","collision_id":"4904287"}
,{"crash_date":"2026-06-05T00:00:00.000","crash_time":"11:05","latitude":"40.723923","longitude":"-73.94751","cross_street_name":"38        MCGUINNESS BLVD","number_of_persons_injured":"0","number_of_pedestrians_injured":"0","number_of_pedestrians_killed":"0","number_of_cyclist_injured":"0","number_of_cyclist_killed":"0","number_of_motorist_injured":"0","number_of_motorist_killed":"0","collision_id":"4904315"}
,{"crash_date":"2026-06-05T00:00:00.000","crash_time":"11:10","latitude":"40.72088","longitude":"-73.99527","cross_street_name":"39        KENMARE ST","number_of_persons_injured":"1","number_of_pedestrians_injured":"0","number_of_pedestrians_killed":"0","number_of_cyclist_injured":"0","number_of_cyclist_killed":"0","number_of_motorist_injured":"1","number_of_motorist_killed":"0","collision_id":"4904717"}
,{"crash_date":"2026-06-05T00:00:00.000","crash_time":"12:00","latitude":"40.71608","longitude":"-74.00117","cross_street_name":"100       CENTRE ST","number_of_persons_injured":"0","number_of_pedestrians_injured":"0","number_of_pedestrians_killed":"0","number_of_cyclist_injured":"0","number_of_cyclist_killed":"0","number_of_motorist_injured":"0","number_of_motorist_killed":"0","collision_id":"4904719"}
,{"crash_date":"2026-06-05T00:00:00.000","crash_time":"12:45","latitude":"40.71633","longitude":"-73.94807","on_street_name":"LEONARD ST","number_of_persons_injured":"0","number_of_pedestrians_injured":"0","number_of_pedestrians_killed":"0","number_of_cyclist_injured":"0","number_of_cyclist_killed":"0","number_of_motorist_injured":"0","number_of_motorist_killed":"0","collision_id":"4904158"}
,{"crash_date":"2026-06-05T00:00:00.000","crash_time":"13:14","latitude":"40.71395","longitude":"-73.951836","cross_street_name":"518       METROPOLITAN AVE","number_of_persons_injured":"0","number_of_pedestrians_injured":"0","number_of_pedestrians_killed":"0","number_of_cyclist_injured":"0","number_of_cyclist_killed":"0","number_of_motorist_injured":"0","number_of_motorist_killed":"0","collision_id":"4904178"}
,{"crash_date":"2026-06-05T00:00:00.000","crash_time":"13:35","latitude":"40.740875","longitude":"-73.98798","on_street_name":"E 23 ST","off_street_name":"MADISON AVE","number_of_persons_injured":"1","number_of_pedestrians_injured":"0","number_of_pedestrians_killed":"0","number_of_cyclist_injured":"1","number_of_cyclist_killed":"0","number_of_motorist_injured":"0","number_of_motorist_killed":"0","collision_id":"4904517"}
,{"crash_date":"2026-06-05T00:00:00.000","crash_time":"13:43","latitude":"40.725197","longitude":"-73.99824","cross_street_name":"155       MERCER ST","number_of_persons_injured":"0","number_of_pedestrians_injured":"0","number_of_pedestrians_killed":"0","number_of_cyclist_injured":"0","number_of_cyclist_killed":"0","number_of_motorist_injured":"0","number_of_motorist_killed":"0","collision_id":"4904966"}
,{"crash_date":"2026-06-05T00:00:00.000","crash_time":"14:02","latitude":"40.7133","longitude":"-73.967415","on_street_name":"KENT AVE","number_of_persons_injured":"0","number_of_pedestrians_injured":"0","number_of_pedestrians_killed":"0","number_of_cyclist_injured":"0","number_of_cyclist_killed":"0","number_of_motorist_injured":"0","number_of_motorist_killed":"0","collision_id":"4904497"}
,{"crash_date":"2026-06-05T00:00:00.000","crash_time":"14:06","latitude":"40.718822","longitude":"-73.98828","cross_street_name":"114       DELANCEY ST","number_of_persons_injured":"1","number_of_pedestrians_injured":"0","number_of_pedestrians_killed":"0","number_of_cyclist_injured":"1","number_of_cyclist_killed":"0","number_of_motorist_injured":"0","number_of_motorist_killed":"0","collision_id":"4904169"}
,{"crash_date":"2026-06-05T00:00:00.000","crash_time":"15:03","latitude":"40.726437","longitude":"-74.00565","on_street_name":"VANDAM ST","off_street_name":"VARICK ST","number_of_persons_injured":"1","number_of_pedestrians_injured":"1","number_of_pedestrians_killed":"0","number_of_cyclist_injured":"0","number_of_cyclist_killed":"0","number_of_motorist_injured":"0","number_of_motorist_killed":"0","collision_id":"4904974"}
,{"crash_date":"2026-06-05T00:00:00.000","crash_time":"16:24","latitude":"40.732594","longitude":"-73.97441","on_street_name":"E 20 ST","off_street_name":"AVENUE C","number_of_persons_injured":"0","number_of_pedestrians_injured":"0","number_of_pedestrians_killed":"0","number_of_cyclist_injured":"0","number_of_cyclist_killed":"0","number_of_motorist_injured":"0","number_of_motorist_killed":"0","collision_id":"4904515"}
,{"crash_date":"2026-06-05T00:00:00.000","crash_time":"20:05","latitude":"40.718315","longitude":"-73.94659","cross_street_name":"410       MANHATTAN AVE","number_of_persons_injured":"0","number_of_pedestrians_injured":"0","number_of_pedestrians_killed":"0","number_of_cyclist_injured":"0","number_of_cyclist_killed":"0","number_of_motorist_injured":"0","number_of_motorist_killed":"0","collision_id":"4905175"}
,{"crash_date":"2026-06-05T00:00:00.000","crash_time":"2:23","latitude":"40.729088","longitude":"-73.98132","on_street_name":"AVENUE A","number_of_persons_injured":"1","number_of_pedestrians_injured":"0","number_of_pedestrians_killed":"0","number_of_cyclist_injured":"0","number_of_cyclist_killed":"0","number_of_motorist_injured":"1","number_of_motorist_killed":"0","collision_id":"4904284"}
,{"crash_date":"2026-06-05T00:00:00.000","crash_time":"22:56","latitude":"40.718227","longitude":"-74.0027","cross_street_name":"388       BROADWAY","number_of_persons_injured":"1","number_of_pedestrians_injured":"1","number_of_pedestrians_killed":"0","number_of_cyclist_injured":"0","number_of_cyclist_killed":"0","number_of_motorist_injured":"0","number_of_motorist_killed":"0","collision_id":"4904712"}
,{"crash_date":"2026-06-05T00:00:00.000","crash_time":"23:35","latitude":"40.732384","longitude":"-74.01035","on_street_name":"WEST ST","off_street_name":"CHRISTOPHER ST","number_of_persons_injured":"1","number_of_pedestrians_injured":"0","number_of_pedestrians_killed":"0","number_of_cyclist_injured":"0","number_of_cyclist_killed":"0","number_of_motorist_injured":"1","number_of_motorist_killed":"0","collision_id":"4904568"}
,{"crash_date":"2026-06-05T00:00:00.000","crash_time":"6:20","latitude":"40.71415","longitude":"-73.95674","cross_street_name":"340       METROPOLITAN AVE","number_of_persons_injured":"1","number_of_pedestrians_injured":"0","number_of_pedestrians_killed":"0","number_of_cyclist_injured":"1","number_of_cyclist_killed":"0","number_of_motorist_injured":"0","number_of_motorist_killed":"0","collision_id":"4904179"}
,{"crash_date":"2026-06-05T00:00:00.000","crash_time":"6:48","latitude":"40.724136","longitude":"-73.99261","on_street_name":"BOWERY","off_street_name":"E HOUSTON ST","number_of_persons_injured":"1","number_of_pedestrians_injured":"0","number_of_pedestrians_killed":"0","number_of_cyclist_injured":"0","number_of_cyclist_killed":"0","number_of_motorist_injured":"0","number_of_motorist_killed":"0","collision_id":"4904269"}
,{"crash_date":"2026-06-05T00:00:00.000","crash_time":"7:12","latitude":"40.742374","longitude":"-74.00879","on_street_name":"WEST ST","off_street_name":"W 14 ST","number_of_persons_injured":"0","number_of_pedestrians_injured":"0","number_of_pedestrians_killed":"0","number_of_cyclist_injured":"0","number_of_cyclist_killed":"0","number_of_motorist_injured":"0","number_of_motorist_killed":"0","collision_id":"4904570"}
,{"crash_date":"2026-06-05T00:00:00.000","crash_time":"9:45","latitude":"40.720238","longitude":"-73.944405","on_street_name":"MEEKER AVE","off_street_name":"HUMBOLDT ST","number_of_persons_injured":"0","number_of_pedestrians_injured":"0","number_of_pedestrians_killed":"0","number_of_cyclist_injured":"0","number_of_cyclist_killed":"0","number_of_motorist_injured":"0","number_of_motorist_killed":"0","collision_id":"4904159"}
,{"crash_date":"2026-06-06T00:00:00.000","crash_time":"12:10","latitude":"40.71397","longitude":"-73.98042","cross_street_name":"551       GRAND ST","number_of_persons_injured":"1","number_of_pedestrians_injured":"1","number_of_pedestrians_killed":"0","number_of_cyclist_injured":"0","number_of_cyclist_killed":"0","number_of_motorist_injured":"0","number_of_motorist_killed":"0","collision_id":"4904396"}
,{"crash_date":"2026-06-06T00:00:00.000","crash_time":"12:45","latitude":"40.740273","longitude":"-73.99572","cross_street_name":"115       W 18 ST","number_of_persons_injured":"1","number_of_pedestrians_injured":"0","number_of_pedestrians_killed":"0","number_of_cyclist_injured":"0","number_of_cyclist_killed":"0","number_of_motorist_injured":"1","number_of_motorist_killed":"0","collision_id":"4904514"}
,{"crash_date":"2026-06-06T00:00:00.000","crash_time":"13:22","latitude":"40.73643","longitude":"-73.95599","cross_street_name":"66        CLAY ST","number_of_persons_injured":"2","number_of_pedestrians_injured":"0","number_of_pedestrians_killed":"0","number_of_cyclist_injured":"0","number_of_cyclist_killed":"0","number_of_motorist_injured":"2","number_of_motorist_killed":"0","collision_id":"4904793"}
,{"crash_date":"2026-06-06T00:00:00.000","crash_time":"13:40","latitude":"40.733204","longitude":"-74.0098","on_street_name":"W 10 ST","off_street_name":"WEEHAWKEN ST","number_of_persons_injured":"0","number_of_pedestrians_injured":"0","number_of_pedestrians_killed":"0","number_of_cyclist_injured":"0","number_of_cyclist_killed":"0","number_of_motorist_injured":"0","number_of_motorist_killed":"0","collision_id":"4905471"}
,{"crash_date":"2026-06-06T00:00:00.000","crash_time":"1:35","latitude":"40.729","longitude":"-74.005455","cross_street_name":"225       VARICK ST","number_of_persons_injured":"1","number_of_pedestrians_injured":"0","number_of_pedestrians_killed":"0","number_of_cyclist_injured":"0","number_of_cyclist_killed":"0","number_of_motorist_injured":"1","number_of_motorist_killed":"0","collision_id":"4904569"}
,{"crash_date":"2026-06-06T00:00:00.000","crash_time":"15:20","latitude":"40.713028","longitude":"-73.954445","on_street_name":"BROOKLYN QUEENS EXPRESSWAY","number_of_persons_injured":"1","number_of_pedestrians_injured":"0","number_of_pedestrians_killed":"0","number_of_cyclist_injured":"0","number_of_cyclist_killed":"0","number_of_motorist_injured":"1","number_of_motorist_killed":"0","collision_id":"4904491"}
,{"crash_date":"2026-06-06T00:00:00.000","crash_time":"15:20","latitude":"40.740917","longitude":"-73.952255","on_street_name":"BORDEN AVE","off_street_name":"11 ST","number_of_persons_injured":"0","number_of_pedestrians_injured":"0","number_of_pedestrians_killed":"0","number_of_cyclist_injured":"0","number_of_cyclist_killed":"0","number_of_motorist_injured":"0","number_of_motorist_killed":"0","collision_id":"4904973"}
,{"crash_date":"2026-06-06T00:00:00.000","crash_time":"16:30","latitude":"40.709835","longitude":"-74.01488","on_street_name":"WEST ST","number_of_persons_injured":"0","number_of_pedestrians_injured":"0","number_of_pedestrians_killed":"0","number_of_cyclist_injured":"0","number_of_cyclist_killed":"0","number_of_motorist_injured":"0","number_of_motorist_killed":"0","collision_id":"4904969"}
,{"crash_date":"2026-06-06T00:00:00.000","crash_time":"17:00","latitude":"40.732594","longitude":"-73.97441","on_street_name":"AVENUE C","off_street_name":"E 20 ST","number_of_persons_injured":"2","number_of_pedestrians_injured":"0","number_of_pedestrians_killed":"0","number_of_cyclist_injured":"0","number_of_cyclist_killed":"0","number_of_motorist_injured":"2","number_of_motorist_killed":"0","collision_id":"4904919"}
,{"crash_date":"2026-06-06T00:00:00.000","crash_time":"17:18","latitude":"40.71816","longitude":"-73.99062","cross_street_name":"88        ALLEN ST","number_of_persons_injured":"0","number_of_pedestrians_injured":"0","number_of_pedestrians_killed":"0","number_of_cyclist_injured":"0","number_of_cyclist_killed":"0","number_of_motorist_injured":"0","number_of_motorist_killed":"0","collision_id":"4904455"}
,{"crash_date":"2026-06-06T00:00:00.000","crash_time":"19:30","latitude":"40.729977","longitude":"-73.952415","cross_street_name":"319       ECKFORD ST","number_of_persons_injured":"0","number_of_pedestrians_injured":"0","number_of_pedestrians_killed":"0","number_of_cyclist_injured":"0","number_of_cyclist_killed":"0","number_of_motorist_injured":"0","number_of_motorist_killed":"0","collision_id":"4904806"}
,{"crash_date":"2026-06-06T00:00:00.000","crash_time":"21:38","latitude":"40.71812","longitude":"-73.985985","cross_street_name":"158       DELANCEY ST","number_of_persons_injured":"1","number_of_pedestrians_injured":"0","number_of_pedestrians_killed":"0","number_of_cyclist_injured":"0","number_of_cyclist_killed":"0","number_of_motorist_injured":"1","number_of_motorist_killed":"0","collision_id":"4904468"}
,{"crash_date":"2026-06-06T00:00:00.000","crash_time":"22:09","latitude":"40.71155","longitude":"-73.99601","cross_street_name":"11        MONROE ST","number_of_persons_injured":"1","number_of_pedestrians_injured":"0","number_of_pedestrians_killed":"0","number_of_cyclist_injured":"1","number_of_cyclist_killed":"0","number_of_motorist_injured":"0","number_of_motorist_killed":"0","collision_id":"4905465"}
,{"crash_date":"2026-06-06T00:00:00.000","crash_time":"4:43","latitude":"40.71907","longitude":"-73.99336","on_street_name":"CHRYSTIE ST","off_street_name":"BROOME ST","number_of_persons_injured":"2","number_of_pedestrians_injured":"0","number_of_pedestrians_killed":"0","number_of_cyclist_injured":"2","number_of_cyclist_killed":"0","number_of_motorist_injured":"0","number_of_motorist_killed":"0","collision_id":"4904715"}
,{"crash_date":"2026-06-06T00:00:00.000","crash_time":"7:52","latitude":"40.721493","longitude":"-74.00898","cross_street_name":"6         HUBERT ST","number_of_persons_injured":"1","number_of_pedestrians_injured":"0","number_of_pedestrians_killed":"0","number_of_cyclist_injured":"0","number_of_cyclist_killed":"0","number_of_motorist_injured":"1","number_of_motorist_killed":"0","collision_id":"4904967"}
,{"crash_date":"2026-06-06T00:00:00.000","crash_time":"9:20","latitude":"40.710247","longitude":"-73.95839","on_street_name":"HAVEMEYER ST","off_street_name":"S 4 ST","number_of_persons_injured":"0","number_of_pedestrians_injured":"0","number_of_pedestrians_killed":"0","number_of_cyclist_injured":"0","number_of_cyclist_killed":"0","number_of_motorist_injured":"0","number_of_motorist_killed":"0","collision_id":"4904500"}
,{"crash_date":"2026-06-07T00:00:00.000","crash_time":"0:37","latitude":"40.728603","longitude":"-74.00532","on_street_name":"W HOUSTON ST","off_street_name":"VARICK ST","number_of_persons_injured":"0","number_of_pedestrians_injured":"0","number_of_pedestrians_killed":"0","number_of_cyclist_injured":"0","number_of_cyclist_killed":"0","number_of_motorist_injured":"0","number_of_motorist_killed":"0","collision_id":"4905736"}
,{"crash_date":"2026-06-07T00:00:00.000","crash_time":"12:45","latitude":"40.727882","longitude":"-74.000015","cross_street_name":"178       THOMPSON ST","number_of_persons_injured":"1","number_of_pedestrians_injured":"1","number_of_pedestrians_killed":"0","number_of_cyclist_injured":"0","number_of_cyclist_killed":"0","number_of_motorist_injured":"0","number_of_motorist_killed":"0","collision_id":"4904584"}
,{"crash_date":"2026-06-07T00:00:00.000","crash_time":"12:58","latitude":"40.72803","longitude":"-73.98239","cross_street_name":"287       E 10 ST","number_of_persons_injured":"1","number_of_pedestrians_injured":"0","number_of_pedestrians_killed":"0","number_of_cyclist_injured":"1","number_of_cyclist_killed":"0","number_of_motorist_injured":"0","number_of_motorist_killed":"0","collision_id":"4905021"}
,{"crash_date":"2026-06-07T00:00:00.000","crash_time":"13:05","latitude":"40.715565","longitude":"-73.99803","cross_street_name":"66        BAYARD ST","number_of_persons_injured":"1","number_of_pedestrians_injured":"1","number_of_pedestrians_killed":"0","number_of_cyclist_injured":"0","number_of_cyclist_killed":"0","number_of_motorist_injured":"0","number_of_motorist_killed":"0","collision_id":"4905013"}
,{"crash_date":"2026-06-07T00:00:00.000","crash_time":"14:17","latitude":"40.731064","longitude":"-74.00141","on_street_name":"W 3 ST","off_street_name":"AVENUE OF THE AMERICAS","number_of_persons_injured":"0","number_of_pedestrians_injured":"0","number_of_pedestrians_killed":"0","number_of_cyclist_injured":"0","number_of_cyclist_killed":"0","number_of_motorist_injured":"0","number_of_motorist_killed":"0","collision_id":"4904652"}
,{"crash_date":"2026-06-07T00:00:00.000","crash_time":"16:18","latitude":"40.719635","longitude":"-73.97751","cross_street_name":"442       E HOUSTON ST","number_of_persons_injured":"0","number_of_pedestrians_injured":"0","number_of_pedestrians_killed":"0","number_of_cyclist_injured":"0","number_of_cyclist_killed":"0","number_of_motorist_injured":"0","number_of_motorist_killed":"0","collision_id":"4905070"}
,{"crash_date":"2026-06-07T00:00:00.000","crash_time":"16:20","latitude":"40.709053","longitude":"-73.9671","on_street_name":"WYTHE AVE","off_street_name":"S 9 ST","number_of_persons_injured":"1","number_of_pedestrians_injured":"0","number_of_pedestrians_killed":"0","number_of_cyclist_injured":"1","number_of_cyclist_killed":"0","number_of_motorist_injured":"0","number_of_motorist_killed":"0","collision_id":"4904663"}
,{"crash_date":"2026-06-07T00:00:00.000","crash_time":"16:25","latitude":"40.736668","longitude":"-73.99734","on_street_name":"W 13 ST","off_street_name":"AVENUE OF THE AMERICAS","number_of_persons_injured":"0","number_of_pedestrians_injured":"0","number_of_pedestrians_killed":"0","number_of_cyclist_injured":"0","number_of_cyclist_killed":"0","number_of_motorist_injured":"0","number_of_motorist_killed":"0","collision_id":"4905170"}
,{"crash_date":"2026-06-07T00:00:00.000","crash_time":"20:05","latitude":"40.730724","longitude":"-73.98905","on_street_name":"E 10 ST","off_street_name":"3 AVE","number_of_persons_injured":"1","number_of_pedestrians_injured":"0","number_of_pedestrians_killed":"0","number_of_cyclist_injured":"1","number_of_cyclist_killed":"0","number_of_motorist_injured":"0","number_of_motorist_killed":"0","collision_id":"4904805"}
,{"crash_date":"2026-06-07T00:00:00.000","crash_time":"20:24","latitude":"40.726055","longitude":"-73.983536","on_street_name":"AVENUE A","off_street_name":"E 7 ST","number_of_persons_injured":"1","number_of_pedestrians_injured":"0","number_of_pedestrians_killed":"0","number_of_cyclist_injured":"1","number_of_cyclist_killed":"0","number_of_motorist_injured":"0","number_of_motorist_killed":"0","collision_id":"4904803"}
,{"crash_date":"2026-06-07T00:00:00.000","crash_time":"21:45","latitude":"40.73975","longitude":"-73.98571","cross_street_name":"120       E 23 ST","number_of_persons_injured":"0","number_of_pedestrians_injured":"0","number_of_pedestrians_killed":"0","number_of_cyclist_injured":"0","number_of_cyclist_killed":"0","number_of_motorist_injured":"0","number_of_motorist_killed":"0","collision_id":"4904922"}
,{"crash_date":"2026-06-07T00:00:00.000","crash_time":"22:59","latitude":"40.742504","longitude":"-73.95724","cross_street_name":"2-40      51 AVE","number_of_persons_injured":"0","number_of_pedestrians_injured":"0","number_of_pedestrians_killed":"0","number_of_cyclist_injured":"0","number_of_cyclist_killed":"0","number_of_motorist_injured":"0","number_of_motorist_killed":"0","collision_id":"4904952"}
,{"crash_date":"2026-06-07T00:00:00.000","crash_time":"23:30","latitude":"40.71333","longitude":"-74.011","on_street_name":"W BROADWAY","off_street_name":"BARCLAY ST","number_of_persons_injured":"0","number_of_pedestrians_injured":"0","number_of_pedestrians_killed":"0","number_of_cyclist_injured":"0","number_of_cyclist_killed":"0","number_of_motorist_injured":"0","number_of_motorist_killed":"0","collision_id":"4904971"}
,{"crash_date":"2026-06-07T00:00:00.000","crash_time":"23:45","latitude":"40.718002","longitude":"-73.98659","on_street_name":"DELANCEY ST","off_street_name":"SUFFOLK ST","number_of_persons_injured":"1","number_of_pedestrians_injured":"1","number_of_pedestrians_killed":"0","number_of_cyclist_injured":"0","number_of_cyclist_killed":"0","number_of_motorist_injured":"0","number_of_motorist_killed":"0","collision_id":"4904823"}
,{"crash_date":"2026-06-07T00:00:00.000","crash_time":"3:35","latitude":"40.71074","longitude":"-73.94547","on_street_name":"MANHATTAN AVE","off_street_name":"MAUJER ST","number_of_persons_injured":"1","number_of_pedestrians_injured":"1","number_of_pedestrians_killed":"0","number_of_cyclist_injured":"0","number_of_cyclist_killed":"0","number_of_motorist_injured":"0","number_of_motorist_killed":"0","collision_id":"4904556"}
,{"crash_date":"2026-06-08T00:00:00.000","crash_time":"0:24","latitude":"40.718796","longitude":"-73.98901","on_street_name":"DELANCEY ST","off_street_name":"LUDLOW ST","number_of_persons_injured":"1","number_of_pedestrians_injured":"0","number_of_pedestrians_killed":"0","number_of_cyclist_injured":"0","number_of_cyclist_killed":"0","number_of_motorist_injured":"1","number_of_motorist_killed":"0","collision_id":"4904819"}
,{"crash_date":"2026-06-08T00:00:00.000","crash_time":"10:05","latitude":"40.71056","longitude":"-73.99414","on_street_name":"MARKET SLIP","off_street_name":"CHERRY ST","number_of_persons_injured":"0","number_of_pedestrians_injured":"0","number_of_pedestrians_killed":"0","number_of_cyclist_injured":"0","number_of_cyclist_killed":"0","number_of_motorist_injured":"0","number_of_motorist_killed":"0","collision_id":"4905412"}
,{"crash_date":"2026-06-08T00:00:00.000","crash_time":"11:14","latitude":"40.72291","longitude":"-73.99184","cross_street_name":"215       CHRYSTIE ST","number_of_persons_injured":"1","number_of_pedestrians_injured":"1","number_of_pedestrians_killed":"0","number_of_cyclist_injured":"0","number_of_cyclist_killed":"0","number_of_motorist_injured":"0","number_of_motorist_killed":"0","collision_id":"4905462"}
,{"crash_date":"2026-06-08T00:00:00.000","crash_time":"11:20","latitude":"40.70791","longitude":"-73.94501","on_street_name":"MANHATTAN AVE","off_street_name":"MESEROLE ST","number_of_persons_injured":"0","number_of_pedestrians_injured":"0","number_of_pedestrians_killed":"0","number_of_cyclist_injured":"0","number_of_cyclist_killed":"0","number_of_motorist_injured":"0","number_of_motorist_killed":"0","collision_id":"4905450"}
,{"crash_date":"2026-06-08T00:00:00.000","crash_time":"12:57","latitude":"40.71123","longitude":"-73.98479","on_street_name":"MONTGOMERY ST","off_street_name":"WATER ST","number_of_persons_injured":"1","number_of_pedestrians_injured":"0","number_of_pedestrians_killed":"0","number_of_cyclist_injured":"0","number_of_cyclist_killed":"0","number_of_motorist_injured":"1","number_of_motorist_killed":"0","collision_id":"4905042"}
,{"crash_date":"2026-06-08T00:00:00.000","crash_time":"13:25","latitude":"40.724697","longitude":"-73.97841","on_street_name":"E 8 ST","off_street_name":"AVENUE C","number_of_persons_injured":"1","number_of_pedestrians_injured":"0","number_of_pedestrians_killed":"0","number_of_cyclist_injured":"0","number_of_cyclist_killed":"0","number_of_motorist_injured":"1","number_of_motorist_killed":"0","collision_id":"4905097"}
,{"crash_date":"2026-06-08T00:00:00.000","crash_time":"15:00","latitude":"40.73242","longitude":"-73.98551","cross_street_name":"244       E 14 ST","number_of_persons_injured":"2","number_of_pedestrians_injured":"2","number_of_pedestrians_killed":"0","number_of_cyclist_injured":"0","number_of_cyclist_killed":"0","number_of_motorist_injured":"0","number_of_motorist_killed":"0","collision_id":"4905757"}
,{"crash_date":"2026-06-08T00:00:00.000","crash_time":"15:10","latitude":"40.724693","longitude":"-73.99418","on_street_name":"MOTT ST","off_street_name":"E HOUSTON ST","number_of_persons_injured":"1","number_of_pedestrians_injured":"1","number_of_pedestrians_killed":"0","number_of_cyclist_injured":"0","number_of_cyclist_killed":"0","number_of_motorist_injured":"0","number_of_motorist_killed":"0","collision_id":"4905467"}
,{"crash_date":"2026-06-08T00:00:00.000","crash_time":"16:11","latitude":"40.709774","longitude":"-73.996216","on_street_name":"WATER ST","off_street_name":"CATHERINE SLIP","number_of_persons_injured":"0","number_of_pedestrians_injured":"0","number_of_pedestrians_killed":"0","number_of_cyclist_injured":"0","number_of_cyclist_killed":"0","number_of_motorist_injured":"0","number_of_motorist_killed":"0","collision_id":"4905279"}
,{"crash_date":"2026-06-08T00:00:00.000","crash_time":"16:33","latitude":"40.72899","longitude":"-73.97629","cross_street_name":"635       E 14 ST","number_of_persons_injured":"1","number_of_pedestrians_injured":"0","number_of_pedestrians_killed":"0","number_of_cyclist_injured":"1","number_of_cyclist_killed":"0","number_of_motorist_injured":"0","number_of_motorist_killed":"0","collision_id":"4905733"}
,{"crash_date":"2026-06-08T00:00:00.000","crash_time":"20:00","latitude":"40.714314","longitude":"-73.97481","on_street_name":"WILLIAMSBURG BRIDGE INNER ROADWA","number_of_persons_injured":"0","number_of_pedestrians_injured":"0","number_of_pedestrians_killed":"0","number_of_cyclist_injured":"0","number_of_cyclist_killed":"0","number_of_motorist_injured":"0","number_of_motorist_killed":"0","collision_id":"4905423"}
,{"crash_date":"2026-06-08T00:00:00.000","crash_time":"23:50","latitude":"40.724136","longitude":"-73.99261","on_street_name":"E HOUSTON ST","off_street_name":"BOWERY","number_of_persons_injured":"0","number_of_pedestrians_injured":"0","number_of_pedestrians_killed":"0","number_of_cyclist_injured":"0","number_of_cyclist_killed":"0","number_of_motorist_injured":"0","number_of_motorist_killed":"0","collision_id":"4905716"}
,{"crash_date":"2026-06-08T00:00:00.000","crash_time":"8:35","latitude":"40.74445","longitude":"-73.97303","on_street_name":"1 AVE","off_street_name":"E 35 ST","number_of_persons_injured":"0","number_of_pedestrians_injured":"0","number_of_pedestrians_killed":"0","number_of_cyclist_injured":"0","number_of_cyclist_killed":"0","number_of_motorist_injured":"0","number_of_motorist_killed":"0","collision_id":"4905629"}
,{"crash_date":"2026-06-08T00:00:00.000","crash_time":"9:09","latitude":"40.71129","longitude":"-73.96778","cross_street_name":"15        DUNHAM PL","number_of_persons_injured":"0","number_of_pedestrians_injured":"0","number_of_pedestrians_killed":"0","number_of_cyclist_injured":"0","number_of_cyclist_killed":"0","number_of_motorist_injured":"0","number_of_motorist_killed":"0","collision_id":"4904948"}
,{"crash_date":"2026-06-09T00:00:00.000","crash_time":"0:24","latitude":"40.72019","longitude":"-73.96321","cross_street_name":"22        N 6 ST","number_of_persons_injured":"0","number_of_pedestrians_injured":"0","number_of_pedestrians_killed":"0","number_of_cyclist_injured":"0","number_of_cyclist_killed":"0","number_of_motorist_injured":"0","number_of_motorist_killed":"0","collision_id":"4905174"}
,{"crash_date":"2026-06-09T00:00:00.000","crash_time":"0:40","latitude":"40.731144","longitude":"-73.95948","on_street_name":"JAVA ST","number_of_persons_injured":"0","number_of_pedestrians_injured":"0","number_of_pedestrians_killed":"0","number_of_cyclist_injured":"0","number_of_cyclist_killed":"0","number_of_motorist_injured":"0","number_of_motorist_killed":"0","collision_id":"4905492"}
,{"crash_date":"2026-06-09T00:00:00.000","crash_time":"1:00","latitude":"40.707493","longitude":"-73.94849","cross_street_name":"48        MESEROLE ST","number_of_persons_injured":"0","number_of_pedestrians_injured":"0","number_of_pedestrians_killed":"0","number_of_cyclist_injured":"0","number_of_cyclist_killed":"0","number_of_motorist_injured":"0","number_of_motorist_killed":"0","collision_id":"4905444"}
,{"crash_date":"2026-06-09T00:00:00.000","crash_time":"11:47","latitude":"40.73883","longitude":"-73.98315","on_street_name":"E 23 ST","off_street_name":"3 AVE","number_of_persons_injured":"0","number_of_pedestrians_injured":"0","number_of_pedestrians_killed":"0","number_of_cyclist_injured":"0","number_of_cyclist_killed":"0","number_of_motorist_injured":"0","number_of_motorist_killed":"0","collision_id":"4905484"}
,{"crash_date":"2026-06-09T00:00:00.000","crash_time":"11:53","latitude":"40.719025","longitude":"-73.98977","on_street_name":"DELANCEY ST","off_street_name":"ORCHARD ST","number_of_persons_injured":"0","number_of_pedestrians_injured":"0","number_of_pedestrians_killed":"0","number_of_cyclist_injured":"0","number_of_cyclist_killed":"0","number_of_motorist_injured":"0","number_of_motorist_killed":"0","collision_id":"4905256"}
,{"crash_date":"2026-06-09T00:00:00.000","crash_time":"1:20","latitude":"40.743973","longitude":"-73.98883","cross_street_name":"1140      BROADWAY","number_of_persons_injured":"2","number_of_pedestrians_injured":"0","number_of_pedestrians_killed":"0","number_of_cyclist_injured":"0","number_of_cyclist_killed":"0","number_of_motorist_injured":"2","number_of_motorist_killed":"0","collision_id":"4905179"}
,{"crash_date":"2026-06-09T00:00:00.000","crash_time":"1:31","latitude":"40.72065","longitude":"-74.00063","cross_street_name":"458       BROADWAY","number_of_persons_injured":"2","number_of_pedestrians_injured":"0","number_of_pedestrians_killed":"0","number_of_cyclist_injured":"0","number_of_cyclist_killed":"0","number_of_motorist_injured":"2","number_of_motorist_killed":"0","collision_id":"4905711"}
,{"crash_date":"2026-06-09T00:00:00.000","crash_time":"14:14","latitude":"40.715702","longitude":"-73.95578","on_street_name":"ROEBLING ST","off_street_name":"N 6 ST","number_of_persons_injured":"1","number_of_pedestrians_injured":"1","number_of_pedestrians_killed":"0","number_of_cyclist_injured":"0","number_of_cyclist_killed":"0","number_of_motorist_injured":"0","number_of_motorist_killed":"0","collision_id":"4905753"}
,{"crash_date":"2026-06-09T00:00:00.000","crash_time":"15:09","latitude":"40.74415","longitude":"-73.98435","cross_street_name":"40        E 29 ST","number_of_persons_injured":"1","number_of_pedestrians_injured":"0","number_of_pedestrians_killed":"0","number_of_cyclist_injured":"1","number_of_cyclist_killed":"0","number_of_motorist_injured":"0","number_of_motorist_killed":"0","collision_id":"4905475"}
,{"crash_date":"2026-06-09T00:00:00.000","crash_time":"17:16","latitude":"40.73602","longitude":"-73.98227","on_street_name":"E 20 ST","off_street_name":"2 AVE","number_of_persons_injured":"1","number_of_pedestrians_injured":"0","number_of_pedestrians_killed":"0","number_of_cyclist_injured":"1","number_of_cyclist_killed":"0","number_of_motorist_injured":"0","number_of_motorist_killed":"0","collision_id":"4905480"}
,{"crash_date":"2026-06-09T00:00:00.000","crash_time":"17:35","latitude":"40.723366","longitude":"-73.94128","on_street_name":"KINGSLAND AVE","off_street_name":"DRIGGS AVE","number_of_persons_injured":"1","number_of_pedestrians_injured":"0","number_of_pedestrians_killed":"0","number_of_cyclist_injured":"0","number_of_cyclist_killed":"0","number_of_motorist_injured":"1","number_of_motorist_killed":"0","collision_id":"4905489"}
,{"crash_date":"2026-06-09T00:00:00.000","crash_time":"19:34","latitude":"40.71877","longitude":"-73.98244","cross_street_name":"91        PITT ST","number_of_persons_injured":"1","number_of_pedestrians_injured":"0","number_of_pedestrians_killed":"0","number_of_cyclist_injured":"1","number_of_cyclist_killed":"0","number_of_motorist_injured":"0","number_of_motorist_killed":"0","collision_id":"4905334"}
,{"crash_date":"2026-06-09T00:00:00.000","crash_time":"21:45","latitude":"40.732925","longitude":"-74.00007","on_street_name":"WAVERLY PL","off_street_name":"AVENUE OF THE AMERICAS","number_of_persons_injured":"1","number_of_pedestrians_injured":"0","number_of_pedestrians_killed":"0","number_of_cyclist_injured":"1","number_of_cyclist_killed":"0","number_of_motorist_injured":"0","number_of_motorist_killed":"0","collision_id":"4905464"}
,{"crash_date":"2026-06-10T00:00:00.000","crash_time":"1:00","latitude":"40.738686","longitude":"-74.01003","on_street_name":"WEST ST","off_street_name":"10 AVE","number_of_persons_injured":"3","number_of_pedestrians_injured":"0","number_of_pedestrians_killed":"0","number_of_cyclist_injured":"0","number_of_cyclist_killed":"0","number_of_motorist_injured":"3","number_of_motorist_killed":"0","collision_id":"4905470"}
,{"crash_date":"2026-06-10T00:00:00.000","crash_time":"10:05","latitude":"40.71608","longitude":"-74.00117","cross_street_name":"100       CENTRE ST","number_of_persons_injured":"0","number_of_pedestrians_injured":"0","number_of_pedestrians_killed":"0","number_of_cyclist_injured":"0","number_of_cyclist_killed":"0","number_of_motorist_injured":"0","number_of_motorist_killed":"0","collision_id":"4905600"}
,{"crash_date":"2026-06-10T00:00:00.000","crash_time":"10:26","latitude":"40.715157","longitude":"-74.00211","on_street_name":"WORTH ST","off_street_name":"CENTRE ST","number_of_persons_injured":"1","number_of_pedestrians_injured":"1","number_of_pedestrians_killed":"0","number_of_cyclist_injured":"0","number_of_cyclist_killed":"0","number_of_motorist_injured":"0","number_of_motorist_killed":"0","collision_id":"4905709"}
,{"crash_date":"2026-06-10T00:00:00.000","crash_time":"12:05","latitude":"40.73484","longitude":"-73.989784","cross_street_name":"10        UNION SQ E","number_of_persons_injured":"0","number_of_pedestrians_injured":"0","number_of_pedestrians_killed":"0","number_of_cyclist_injured":"0","number_of_cyclist_killed":"0","number_of_motorist_injured":"0","number_of_motorist_killed":"0","collision_id":"4905606"}
,{"crash_date":"2026-06-10T00:00:00.000","crash_time":"12:25","latitude":"40.713715","longitude":"-73.99802","on_street_name":"E BROADWAY","off_street_name":"CHATHAM SQ","number_of_persons_injured":"1","number_of_pedestrians_injured":"1","number_of_pedestrians_killed":"0","number_of_cyclist_injured":"0","number_of_cyclist_killed":"0","number_of_motorist_injured":"0","number_of_motorist_killed":"0","collision_id":"4905710"}
,{"crash_date":"2026-06-10T00:00:00.000","crash_time":"15:00","latitude":"40.7313","longitude":"-74.01046","on_street_name":"WEST ST","off_street_name":"MORTON ST","number_of_persons_injured":"0","number_of_pedestrians_injured":"0","number_of_pedestrians_killed":"0","number_of_cyclist_injured":"0","number_of_cyclist_killed":"0","number_of_motorist_injured":"0","number_of_motorist_killed":"0","collision_id":"4905740"}
,{"crash_date":"2026-06-10T00:00:00.000","crash_time":"15:12","latitude":"40.731533","longitude":"-73.98948","cross_street_name":"112       E 11 ST","number_of_persons_injured":"0","number_of_pedestrians_injured":"0","number_of_pedestrians_killed":"0","number_of_cyclist_injured":"0","number_of_cyclist_killed":"0","number_of_motorist_injured":"0","number_of_motorist_killed":"0","collision_id":"4905668"}
,{"crash_date":"2026-06-10T00:00:00.000","crash_time":"19:00","latitude":"40.729565","longitude":"-74.00455","cross_street_name":"72        CARMINE ST","number_of_persons_injured":"1","number_of_pedestrians_injured":"0","number_of_pedestrians_killed":"0","number_of_cyclist_injured":"1","number_of_cyclist_killed":"0","number_of_motorist_injured":"0","number_of_motorist_killed":"0","collision_id":"4905739"}
,{"crash_date":"2026-06-10T00:00:00.000","crash_time":"4:48","latitude":"40.73831","longitude":"-73.98774","on_street_name":"E 20 ST","off_street_name":"PARK AVE S","number_of_persons_injured":"0","number_of_pedestrians_injured":"0","number_of_pedestrians_killed":"0","number_of_cyclist_injured":"0","number_of_cyclist_killed":"0","number_of_motorist_injured":"0","number_of_motorist_killed":"0","collision_id":"4905474"}
,{"crash_date":"2026-06-11T00:00:00.000","crash_time":"13:08","latitude":"40.716385","longitude":"-73.961426","on_street_name":"N 3 ST","off_street_name":"BERRY ST","number_of_persons_injured":"1","number_of_pedestrians_injured":"0","number_of_pedestrians_killed":"0","number_of_cyclist_injured":"0","number_of_cyclist_killed":"0","number_of_motorist_injured":"1","number_of_motorist_killed":"0","collision_id":"4905771"}
,{"crash_date":"2026-06-11T00:00:00.000","crash_time":"3:50","latitude":"40.709805","longitude":"-73.99191","on_street_name":"SOUTH ST","off_street_name":"PIKE SLIP","number_of_persons_injured":"0","number_of_pedestrians_injured":"0","number_of_pedestrians_killed":"0","number_of_cyclist_injured":"0","number_of_cyclist_killed":"0","number_of_motorist_injured":"0","number_of_motorist_killed":"0","collision_id":"4905704"}]
